NEMO_rs2_access/__init__.py
NEMO_rs2_access/admin.py
NEMO_rs2_access/api.py
NEMO_rs2_access/app_settings.py
NEMO_rs2_access/apps.py
NEMO_rs2_access/models.py
NEMO_rs2_access/rs2.py
NEMO_rs2_access/sync.py
NEMO_rs2_access/urls.py
NEMO_rs2_access/utilities.py
NEMO_rs2_access/views.py
NEMO_rs2_access/management/__init__.py
NEMO_rs2_access/management/commands/__init__.py
NEMO_rs2_access/management/commands/rs2_sync_access.py
NEMO_rs2_access/management/commands/rs2_sync_readers.py
NEMO_rs2_access/management/commands/rs2_update_current_access_project.py
NEMO_rs2_access/migrations/0001_initial.py
NEMO_rs2_access/migrations/0002_cardholder.py
NEMO_rs2_access/migrations/0003_errorlog.py
NEMO_rs2_access/migrations/0004_errorlog_event_data.py
NEMO_rs2_access/migrations/0005_alter_errorlog_error_type.py
NEMO_rs2_access/migrations/__init__.py
NEMO_rs2_access/templates/NEMO_rs2_access/preferences_default_project.html
NEMO_rs2_access/tests/__init__.py
NEMO_rs2_access/tests/test_rs2.py
NEMO_rs2_access/tests/test_settings.py
nemo_rs2_access-1.6.4.dist-info/licenses/LICENSE
nemo_rs2_access-1.6.4.dist-info/METADATA
nemo_rs2_access-1.6.4.dist-info/WHEEL
nemo_rs2_access-1.6.4.dist-info/top_level.txt
nemo_rs2_access-1.6.4.dist-info/RECORD
