Metadata-Version: 2.4
Name: NEMO-rs2-access
Version: 1.6.4
Summary: Install RS2 access plugin for NEMO
Author-email: Atlantis Labs LLC <atlantis@atlantislabs.io>
License: MIT License
Project-URL: Homepage, https://gitlab.com/nemo-community/atlantis-labs/nemo-rs2-access
Project-URL: Changelog, https://gitlab.com/nemo-community/atlantis-labs/nemo-rs2-access/-/releases
Project-URL: Issues, https://gitlab.com/nemo-community/atlantis-labs/nemo-rs2-access/-/issues
Project-URL: CI, https://gitlab.com/nemo-community/atlantis-labs/nemo-rs2-access/-/pipelines
Keywords: NEMO
Classifier: Development Status :: 5 - Production/Stable
Classifier: Intended Audience :: Developers
Classifier: License :: OSI Approved :: MIT License
Classifier: Programming Language :: Python :: 3.9
Classifier: Programming Language :: Python :: 3.10
Classifier: Programming Language :: Python :: 3.11
Classifier: Programming Language :: Python :: 3.12
Classifier: Programming Language :: Python :: 3.13
Requires-Python: >=3.9
License-File: LICENSE
Requires-Dist: requests
Requires-Dist: django
Requires-Dist: djangorestframework
Provides-Extra: nemo-ce
Requires-Dist: NEMO-CE; extra == "nemo-ce"
Provides-Extra: nemo
Requires-Dist: NEMO>=4.3.0; extra == "nemo"
Provides-Extra: dev-tools
Requires-Dist: pre-commit; extra == "dev-tools"
Requires-Dist: djlint; extra == "dev-tools"
Requires-Dist: black; extra == "dev-tools"
Dynamic: license-file
